table.py
circuitpython_table-0.2.0.dist-info/LICENSE
circuitpython_table-0.2.0.dist-info/METADATA
circuitpython_table-0.2.0.dist-info/WHEEL
circuitpython_table-0.2.0.dist-info/top_level.txt
circuitpython_table-0.2.0.dist-info/RECORD
